wheke_sqlmodel/__init__.py
wheke_sqlmodel/_cli.py
wheke_sqlmodel/_pod.py
wheke_sqlmodel/_service.py
wheke_sqlmodel/_settings.py
wheke_sqlmodel/py.typed
wheke_sqlmodel-0.3.0.dist-info/METADATA
wheke_sqlmodel-0.3.0.dist-info/WHEEL
wheke_sqlmodel-0.3.0.dist-info/top_level.txt
wheke_sqlmodel-0.3.0.dist-info/RECORD
