Metadata-Version: 2.4
Name: wheke-sqlmodel
Version: 0.3.0
Summary: Add sql capabilities to wheke with SQLModel
Requires-Python: >=3.12
Requires-Dist: aiosqlite
Requires-Dist: anyio
Requires-Dist: sqlmodel
Requires-Dist: wheke
